<?xml version="1.0" encoding="utf-8"?>
<metadata xml:lang="en">
  <Esri>
    <CreaDate>20131230</CreaDate>
    <CreaTime>18483800</CreaTime>
    <ArcGISFormat>1.0</ArcGISFormat>
    <ArcGISstyle>FGDC CSDGM Metadata</ArcGISstyle>
    <SyncOnce>FALSE</SyncOnce>
    <DataProperties>
      <itemProps>
        <itemName Sync="TRUE">comonth</itemName>
        <relatedItems>
          <item>
            <itemName />
          </item>
          <item>
            <itemName />
            <itemType Sync="TRUE">Relationship</itemType>
          </item>
          <item>
            <itemName />
            <itemType Sync="TRUE">Relationship</itemType>
          </item>
          <item>
            <itemName Sync="TRUE">zComponent_Comonth</itemName>
            <itemType Sync="TRUE">Relationship</itemType>
          </item>
        </relatedItems>
        <itemLocation>
          <linkage Sync="TRUE">file://\\ARCNELI95L00052\E$\Geodata\2013\TemplateDB\Template_FGDB_CONUS_AlbersNAD1983.gdb</linkage>
          <protocol Sync="TRUE">Local Area Network</protocol>
        </itemLocation>
        <imsContentType Sync="TRUE">002</imsContentType>
      </itemProps>
    </DataProperties>
    <SyncDate>20131230</SyncDate>
    <SyncTime>18494500</SyncTime>
    <ModDate>20131230</ModDate>
    <ModTime>18494500</ModTime>
  </Esri>
  <mdLang>
    <languageCode value="eng" />
    <countryCode value="USA" Sync="TRUE" />
  </mdLang>
  <mdChar>
    <CharSetCd value="004" />
  </mdChar>
  <mdHrLv>
    <ScopeCd value="005" />
  </mdHrLv>
  <mdDateSt>20131230</mdDateSt>
  <mdStanName>ArcGIS Metadata</mdStanName>
  <mdStanVer>1.0</mdStanVer>
  <dataIdInfo>
    <idCitation>
      <resTitle>COMONTH</resTitle>
      <presForm>
        <PresFormCd value="001" />
      </presForm>
      <presForm>
        <fgdcGeoform>tabular digital data</fgdcGeoform>
      </presForm>
    </idCitation>
    <idAbs>The Component Month table lists the monthly flooding and ponding characteristics for the referenced map unit component. This table has one row for each month of the year.</idAbs>
    <idPurp>Component Month Table</idPurp>
    <dataLang>
      <languageCode value="eng" />
      <countryCode value="USA" Sync="TRUE" />
    </dataLang>
    <envirDesc>Microsoft Windows 7 Version 6.1 (Build 7601) Service Pack 1; Esri ArcGIS 10.1.1.3143</envirDesc>
    <spatRpType>
      <SpatRepTypCd value="003" Sync="TRUE" />
    </spatRpType>
  </dataIdInfo>
  <eainfo>
    <detailed Name="comonth">
      <enttyp>
        <enttypl>comonth</enttypl>
        <enttypt Sync="TRUE">Table</enttypt>
        <enttypc Sync="TRUE">0</enttypc>
      </enttyp>
      <attr>
        <attrlabl>OBJECTID</attrlabl>
        <attrdef>Internal feature number.</attrdef>
        <attrdefs>Esri</attrdefs>
        <attrdomv>
          <udom>Sequential unique whole numbers that are automatically generated.</udom>
        </attrdomv>
        <attalias Sync="TRUE">OBJECTID</attalias>
        <attrtype Sync="TRUE">OID</attrtype>
        <attwidth Sync="TRUE">4</attwidth>
        <atprecis Sync="TRUE">0</atprecis>
        <attscale Sync="TRUE">0</attscale>
      </attr>
      <attr>
        <attrlabl>ponddep_h</attrlabl>
        <attrdef>The depth of surface water that is ponding on the soil.</attrdef>
        <attalias Sync="TRUE">Ponding Depth - High Value</attalias>
        <attrtype Sync="TRUE">SmallInteger</attrtype>
        <attwidth Sync="TRUE">2</attwidth>
        <atprecis Sync="TRUE">0</atprecis>
        <attscale Sync="TRUE">0</attscale>
      </attr>
      <attr>
        <attrlabl>dlyavgprecip_l</attrlabl>
        <attrdef>The daily average precipitation for the referenced month. Commonly calculated as the total precipitation for the month divided by the number of days in the month. (February nominally has 28 days).</attrdef>
        <attalias Sync="TRUE">Daily Precip - Low Value</attalias>
        <attrtype Sync="TRUE">SmallInteger</attrtype>
        <attwidth Sync="TRUE">2</attwidth>
        <atprecis Sync="TRUE">0</atprecis>
        <attscale Sync="TRUE">0</attscale>
      </attr>
      <attr>
        <attrlabl>ponddep_l</attrlabl>
        <attrdef>The depth of surface water that is ponding on the soil.</attrdef>
        <attalias Sync="TRUE">Ponding Depth - Low Value</attalias>
        <attrtype Sync="TRUE">SmallInteger</attrtype>
        <attwidth Sync="TRUE">2</attwidth>
        <atprecis Sync="TRUE">0</atprecis>
        <attscale Sync="TRUE">0</attscale>
      </attr>
      <attr>
        <attrlabl>ponddurcl</attrlabl>
        <attrdef>The average duration, or length of time, of the ponding occurrence. (NSSH)</attrdef>
        <attalias Sync="TRUE">Ponding Duration</attalias>
        <attrtype Sync="TRUE">String</attrtype>
        <attwidth Sync="TRUE">254</attwidth>
        <atprecis Sync="TRUE">0</atprecis>
        <attscale Sync="TRUE">0</attscale>
      </attr>
      <attr>
        <attrlabl>floddurcl</attrlabl>
        <attrdef>Average duration of inundation per flood occurrence and expressed as a class. (NSSH)</attrdef>
        <attalias Sync="TRUE">Flooding Duration</attalias>
        <attrtype Sync="TRUE">String</attrtype>
        <attwidth Sync="TRUE">254</attwidth>
        <atprecis Sync="TRUE">0</atprecis>
        <attscale Sync="TRUE">0</attscale>
      </attr>
      <attr>
        <attrlabl>comonthkey</attrlabl>
        <attrdef>A non-connotative string of characters used to uniquely identify a record in the Component Month table.</attrdef>
        <attalias Sync="TRUE">Component Month Key</attalias>
        <attrtype Sync="TRUE">String</attrtype>
        <attwidth Sync="TRUE">30</attwidth>
        <atprecis Sync="TRUE">0</atprecis>
        <attscale Sync="TRUE">0</attscale>
      </attr>
      <attr>
        <attrlabl>dlyavgpotet_h</attrlabl>
        <attrdef>Daily average potential evapotranspiration for the referenced month.</attrdef>
        <attalias Sync="TRUE">Daily ET - High Value</attalias>
        <attrtype Sync="TRUE">SmallInteger</attrtype>
        <attwidth Sync="TRUE">2</attwidth>
        <atprecis Sync="TRUE">0</atprecis>
        <attscale Sync="TRUE">0</attscale>
      </attr>
      <attr>
        <attrlabl>cokey</attrlabl>
        <attrdef>The unique identifier of a record in the Component table. Use this column to join the Component Month table to the Component table.</attrdef>
        <attalias Sync="TRUE">cokey</attalias>
        <attrtype Sync="TRUE">String</attrtype>
        <attwidth Sync="TRUE">30</attwidth>
        <atprecis Sync="TRUE">0</atprecis>
        <attscale Sync="TRUE">0</attscale>
      </attr>
      <attr>
        <attrlabl>dlyavgpotet_r</attrlabl>
        <attrdef>Daily average potential evapotranspiration for the referenced month.</attrdef>
        <attalias Sync="TRUE">Daily ET - Representative Value</attalias>
        <attrtype Sync="TRUE">SmallInteger</attrtype>
        <attwidth Sync="TRUE">2</attwidth>
        <atprecis Sync="TRUE">0</atprecis>
        <attscale Sync="TRUE">0</attscale>
      </attr>
      <attr>
        <attrlabl>dlyavgprecip_r</attrlabl>
        <attrdef>The daily average precipitation for the referenced month. Commonly calculated as the total precipitation for the month divided by the number of days in the month. (February nominally has 28 days).</attrdef>
        <attalias Sync="TRUE">Daily Precip - Representative Value</attalias>
        <attrtype Sync="TRUE">SmallInteger</attrtype>
        <attwidth Sync="TRUE">2</attwidth>
        <atprecis Sync="TRUE">0</atprecis>
        <attscale Sync="TRUE">0</attscale>
      </attr>
      <attr>
        <attrlabl>dlyavgprecip_h</attrlabl>
        <attrdef>The daily average precipitation for the referenced month. Commonly calculated as the total precipitation for the month divided by the number of days in the month. (February nominally has 28 days).</attrdef>
        <attalias Sync="TRUE">Daily Precip - High Value</attalias>
        <attrtype Sync="TRUE">SmallInteger</attrtype>
        <attwidth Sync="TRUE">2</attwidth>
        <atprecis Sync="TRUE">0</atprecis>
        <attscale Sync="TRUE">0</attscale>
      </attr>
      <attr>
        <attrlabl>month</attrlabl>
        <attrdef>One of the twelve months of the year.</attrdef>
        <attalias Sync="TRUE">month</attalias>
        <attrtype Sync="TRUE">String</attrtype>
        <attwidth Sync="TRUE">254</attwidth>
        <atprecis Sync="TRUE">0</atprecis>
        <attscale Sync="TRUE">0</attscale>
      </attr>
      <attr>
        <attrlabl>ponddep_r</attrlabl>
        <attrdef>The depth of surface water that is ponding on the soil.</attrdef>
        <attalias Sync="TRUE">Ponding Depth - Representative Value</attalias>
        <attrtype Sync="TRUE">SmallInteger</attrtype>
        <attwidth Sync="TRUE">2</attwidth>
        <atprecis Sync="TRUE">0</atprecis>
        <attscale Sync="TRUE">0</attscale>
      </attr>
      <attr>
        <attrlabl>monthseq</attrlabl>
        <attrdef>An interger number used to sequence the months of the year in their proper order.</attrdef>
        <attalias Sync="TRUE">Month Sequence</attalias>
        <attrtype Sync="TRUE">SmallInteger</attrtype>
        <attwidth Sync="TRUE">2</attwidth>
        <atprecis Sync="TRUE">0</atprecis>
        <attscale Sync="TRUE">0</attscale>
      </attr>
      <attr>
        <attrlabl>pondfreqcl</attrlabl>
        <attrdef>The number of times ponding occurs over a period of time. (SSM)</attrdef>
        <attalias Sync="TRUE">Ponding Frequency</attalias>
        <attrtype Sync="TRUE">String</attrtype>
        <attwidth Sync="TRUE">254</attwidth>
        <atprecis Sync="TRUE">0</atprecis>
        <attscale Sync="TRUE">0</attscale>
      </attr>
      <attr>
        <attrlabl>flodfreqcl</attrlabl>
        <attrdef>The annual probability of a flood event expressed as a class. (SSM).</attrdef>
        <attalias Sync="TRUE">Flooding Frequency</attalias>
        <attrtype Sync="TRUE">String</attrtype>
        <attwidth Sync="TRUE">254</attwidth>
        <atprecis Sync="TRUE">0</atprecis>
        <attscale Sync="TRUE">0</attscale>
      </attr>
      <attr>
        <attrlabl>dlyavgpotet_l</attrlabl>
        <attrdef>Daily average potential evapotranspiration for the referenced month.</attrdef>
        <attalias Sync="TRUE">Daily ET - Low Value</attalias>
        <attrtype Sync="TRUE">SmallInteger</attrtype>
        <attwidth Sync="TRUE">2</attwidth>
        <atprecis Sync="TRUE">0</atprecis>
        <attscale Sync="TRUE">0</attscale>
      </attr>
    </detailed>
  </eainfo>
  <distInfo>
    <distFormat>
      <formatName Sync="TRUE">File Geodatabase Table</formatName>
    </distFormat>
  </distInfo>
  <mdHrLvName Sync="TRUE">dataset</mdHrLvName>
</metadata>